{
    "swagger": "2.0",
    "info": {
        "description": "Esta é a documentação da API controlF.",
        "title": "controlF API",
        "contact": {},
        "version": "1.0"
    },
    "host": "localhost:7002",
    "basePath": "/api",
    "paths": {
        "/auth/logout": {
            "post": {
                "security": [
                    {
                        "BearerAuth": []
                    }
                ],
                "description": "Invalida o token JWT do usuário, encerrando a sessão.",
                "consumes": [
                    "application/json"
                ],
                "produces": [
                    "application/json"
                ],
                "tags": [
                    "Auth"
                ],
                "summary": "Faz logout do usuário",
                "responses": {
                    "200": {
                        "description": "OK"
                    },
                    "500": {
                        "description": "Erro interno do servidor",
                        "schema": {
                            "$ref": "#/definitions/domain.ErrorResponse"
                        }
                    }
                }
            }
        },
        "/auth/token": {
            "post": {
                "description": "Recebe credenciais de login (email e senha) e retorna um token JWT para acesso autenticado.",
                "consumes": [
                    "application/json"
                ],
                "produces": [
                    "application/json"
                ],
                "tags": [
                    "Auth"
                ],
                "summary": "Autentica um usuário e retorna um token JWT",
                "parameters": [
                    {
                        "description": "Credenciais do usuário",
                        "name": "credentials",
                        "in": "body",
                        "required": true,
                        "schema": {
                            "$ref": "#/definitions/auth.LoginRequest"
                        }
                    }
                ],
                "responses": {
                    "200": {
                        "description": "OK",
                        "schema": {
                            "$ref": "#/definitions/auth.LoginResponse"
                        }
                    },
                    "400": {
                        "description": "Dados inválidos",
                        "schema": {
                            "$ref": "#/definitions/domain.ErrorResponse"
                        }
                    },
                    "401": {
                        "description": "Credenciais inválidas",
                        "schema": {
                            "$ref": "#/definitions/domain.ErrorResponse"
                        }
                    },
                    "500": {
                        "description": "Erro interno do servidor",
                        "schema": {
                            "$ref": "#/definitions/domain.ErrorResponse"
                        }
                    }
                }
            }
        },
        "/users": {
            "post": {
                "description": "Registra um novo usuário com os dados fornecidos.",
                "consumes": [
                    "application/json"
                ],
                "produces": [
                    "application/json"
                ],
                "tags": [
                    "Users"
                ],
                "summary": "Registra um novo usuário",
                "parameters": [
                    {
                        "description": "Dados de registro do usuário",
                        "name": "user",
                        "in": "body",
                        "required": true,
                        "schema": {
                            "$ref": "#/definitions/user.UserRegister"
                        }
                    }
                ],
                "responses": {
                    "201": {
                        "description": "Created",
                        "schema": {
                            "$ref": "#/definitions/user.UserDto"
                        }
                    },
                    "400": {
                        "description": "Dados inválidos",
                        "schema": {
                            "$ref": "#/definitions/domain.ErrorResponse"
                        }
                    },
                    "500": {
                        "description": "Erro interno do servidor",
                        "schema": {
                            "$ref": "#/definitions/domain.ErrorResponse"
                        }
                    }
                }
            }
        },
        "/users/{userId}": {
            "get": {
                "security": [
                    {
                        "BearerAuth": []
                    }
                ],
                "description": "Retorna um usuário a partir do ID",
                "consumes": [
                    "application/json"
                ],
                "produces": [
                    "application/json"
                ],
                "tags": [
                    "Users"
                ],
                "summary": "Retorna um usuário",
                "parameters": [
                    {
                        "type": "string",
                        "description": "ID do usuário",
                        "name": "userId",
                        "in": "path",
                        "required": true
                    }
                ],
                "responses": {
                    "200": {
                        "description": "OK",
                        "schema": {
                            "$ref": "#/definitions/user.UserDto"
                        }
                    },
                    "400": {
                        "description": "ID de usuário inválido",
                        "schema": {
                            "$ref": "#/definitions/domain.ErrorResponse"
                        }
                    },
                    "404": {
                        "description": "Usuário não encontrado",
                        "schema": {
                            "$ref": "#/definitions/domain.ErrorResponse"
                        }
                    },
                    "500": {
                        "description": "Erro interno do servidor",
                        "schema": {
                            "$ref": "#/definitions/domain.ErrorResponse"
                        }
                    }
                }
            },
            "put": {
                "security": [
                    {
                        "BearerAuth": []
                    }
                ],
                "description": "Atualiza os dados de um usuário específico.",
                "consumes": [
                    "application/json"
                ],
                "produces": [
                    "application/json"
                ],
                "tags": [
                    "Users"
                ],
                "summary": "Atualiza um usuário existente",
                "parameters": [
                    {
                        "type": "string",
                        "description": "ID do usuário",
                        "name": "userId",
                        "in": "path",
                        "required": true
                    },
                    {
                        "description": "Dados de atualização do usuário",
                        "name": "user",
                        "in": "body",
                        "required": true,
                        "schema": {
                            "$ref": "#/definitions/user.UserUpdate"
                        }
                    }
                ],
                "responses": {
                    "202": {
                        "description": "Accepted",
                        "schema": {
                            "$ref": "#/definitions/user.UserDto"
                        }
                    },
                    "400": {
                        "description": "Dados inválidos ou ID de usuário inválido",
                        "schema": {
                            "$ref": "#/definitions/domain.ErrorResponse"
                        }
                    },
                    "404": {
                        "description": "Usuário não encontrado",
                        "schema": {
                            "$ref": "#/definitions/domain.ErrorResponse"
                        }
                    },
                    "500": {
                        "description": "Erro interno do servidor",
                        "schema": {
                            "$ref": "#/definitions/domain.ErrorResponse"
                        }
                    }
                }
            }
        },
        "/users/{userId}/password": {
            "put": {
                "security": [
                    {
                        "BearerAuth": []
                    }
                ],
                "description": "Atualiza a senha de um usuário específico, exigindo a senha antiga e a nova senha.",
                "consumes": [
                    "application/json"
                ],
                "produces": [
                    "application/json"
                ],
                "tags": [
                    "Users"
                ],
                "summary": "Atualiza a senha de um usuário",
                "parameters": [
                    {
                        "type": "string",
                        "description": "ID do usuário",
                        "name": "userId",
                        "in": "path",
                        "required": true
                    },
                    {
                        "description": "Dados de atualização de senha",
                        "name": "password",
                        "in": "body",
                        "required": true,
                        "schema": {
                            "$ref": "#/definitions/user.UserUpdatePassword"
                        }
                    }
                ],
                "responses": {
                    "202": {
                        "description": "Accepted",
                        "schema": {
                            "$ref": "#/definitions/user.UserDto"
                        }
                    },
                    "400": {
                        "description": "Dados inválidos, ID de usuário inválido ou senha antiga incorreta",
                        "schema": {
                            "$ref": "#/definitions/domain.ErrorResponse"
                        }
                    },
                    "404": {
                        "description": "Usuário não encontrado",
                        "schema": {
                            "$ref": "#/definitions/domain.ErrorResponse"
                        }
                    },
                    "500": {
                        "description": "Erro interno do servidor",
                        "schema": {
                            "$ref": "#/definitions/domain.ErrorResponse"
                        }
                    }
                }
            }
        }
    },
    "definitions": {
        "auth.LoginRequest": {
            "type": "object",
            "required": [
                "email",
                "password"
            ],
            "properties": {
                "email": {
                    "type": "string"
                },
                "password": {
                    "type": "string",
                    "minLength": 8
                }
            }
        },
        "auth.LoginResponse": {
            "type": "object",
            "properties": {
                "token": {
                    "type": "string"
                }
            }
        },
        "domain.ErrorDetail": {
            "type": "object",
            "properties": {
                "field": {
                    "type": "string"
                },
                "message": {
                    "type": "string"
                }
            }
        },
        "domain.ErrorResponse": {
            "type": "object",
            "properties": {
                "details": {
                    "description": "phrase",
                    "type": "array",
                    "items": {
                        "$ref": "#/definitions/domain.ErrorDetail"
                    }
                },
                "error": {
                    "description": "code",
                    "type": "string"
                }
            }
        },
        "models.UserType": {
            "type": "integer",
            "format": "int32",
            "enum": [
                1,
                2,
                3
            ],
            "x-enum-comments": {
                "UserTypeCompanyAdmin": "Usuário admin de uma empresa",
                "UserTypeCompanyMember": "Usuário membro de uma empresa",
                "UserTypePersonal": "Usuário de conta pessoal"
            },
            "x-enum-descriptions": [
                "Usuário de conta pessoal",
                "Usuário admin de uma empresa",
                "Usuário membro de uma empresa"
            ],
            "x-enum-varnames": [
                "UserTypePersonal",
                "UserTypeCompanyAdmin",
                "UserTypeCompanyMember"
            ]
        },
        "user.UserDto": {
            "type": "object",
            "properties": {
                "company_id": {
                    "type": "string"
                },
                "email": {
                    "type": "string"
                },
                "id": {
                    "type": "string"
                },
                "name": {
                    "type": "string"
                },
                "user_type": {
                    "$ref": "#/definitions/models.UserType"
                }
            }
        },
        "user.UserRegister": {
            "type": "object",
            "required": [
                "email",
                "name",
                "password"
            ],
            "properties": {
                "email": {
                    "type": "string"
                },
                "name": {
                    "type": "string"
                },
                "password": {
                    "type": "string",
                    "minLength": 8
                }
            }
        },
        "user.UserUpdate": {
            "type": "object",
            "properties": {
                "companyId": {
                    "type": "string"
                },
                "email": {
                    "type": "string"
                },
                "name": {
                    "type": "string"
                },
                "type": {
                    "type": "string"
                }
            }
        },
        "user.UserUpdatePassword": {
            "type": "object",
            "required": [
                "newPassword",
                "newPasswordConfirm",
                "oldPassword"
            ],
            "properties": {
                "newPassword": {
                    "type": "string",
                    "minLength": 6
                },
                "newPasswordConfirm": {
                    "type": "string",
                    "minLength": 6
                },
                "oldPassword": {
                    "type": "string",
                    "minLength": 6
                }
            }
        }
    },
    "securityDefinitions": {
        "BearerAuth": {
            "type": "apiKey",
            "name": "Authorization",
            "in": "header"
        }
    }
}